youscan_ir_client/__init__.py
youscan_ir_client/client.py
youscan_ir_client/config.py
youscan_ir_client/entities.py
youscan_ir_client/factories.py
youscan_ir_client/py.typed
youscan_ir_client-24.11.0.dist-info/LICENSE
youscan_ir_client-24.11.0.dist-info/METADATA
youscan_ir_client-24.11.0.dist-info/WHEEL
youscan_ir_client-24.11.0.dist-info/top_level.txt
youscan_ir_client-24.11.0.dist-info/RECORD
