Metadata-Version: 2.1
Name: youscan-ir-client
Version: 24.11.0
Home-page: https://tbd
License: Apache 2
Classifier: License :: OSI Approved :: Apache Software License
Classifier: Programming Language :: Python :: 3
Requires-Python: >=3.7
License-File: LICENSE
Requires-Dist: aiohttp>=3.7
Provides-Extra: dev
Requires-Dist: mypy==0.982; extra == "dev"
Requires-Dist: pre-commit==2.20.0; extra == "dev"
Requires-Dist: pytest==7.2.0; extra == "dev"
Requires-Dist: pytest-cov==4.0.0; extra == "dev"
Requires-Dist: pytest-asyncio==0.20.1; extra == "dev"
Requires-Dist: types-PyYAML; extra == "dev"
